jaconvV2/__init__.py
jaconvV2/compat.py
jaconvV2/conv_table.py
jaconvV2/jaconv.py
jaconvV2-0.4.data/data/CHANGES.rst
jaconvV2-0.4.data/data/README.rst
jaconvV2-0.4.dist-info/LICENSE
jaconvV2-0.4.dist-info/METADATA
jaconvV2-0.4.dist-info/WHEEL
jaconvV2-0.4.dist-info/top_level.txt
jaconvV2-0.4.dist-info/RECORD
