Metadata-Version: 2.1
Name: jaconvV2
Version: 0.4
Summary: Pure-Python Japanese character interconverter for Hiragana, Katakana, Hankaku, Zenkaku, as well as Zenkaku or Hankaku Tester
Home-page: https://github.com/MikimotoH/jaconv
Author: Miki Liu
Author-email: MikimotoH@gmail.com
License: MIT License
Keywords: Japanese converter,Japanese,text preprocessing,half-width kana,Hiragana,Katakana,Hankaku,Zenkaku,transliteration,Julius
Platform: POSIX
Platform: Windows
Platform: Unix
Platform: MacOS
Classifier: Development Status :: 4 - Beta
Classifier: Intended Audience :: Developers
Classifier: Intended Audience :: Information Technology
Classifier: License :: OSI Approved :: MIT License
Classifier: Natural Language :: Japanese
Classifier: Operating System :: MacOS
Classifier: Operating System :: Microsoft
Classifier: Operating System :: POSIX
Classifier: Programming Language :: Python :: 2.7
Classifier: Programming Language :: Python :: 3.4
Classifier: Programming Language :: Python :: 3.5
Classifier: Programming Language :: Python :: 3.6
Classifier: Programming Language :: Python :: 3.7
Classifier: Programming Language :: Python :: 3.8
Classifier: Programming Language :: Python :: 3.9
Classifier: Topic :: Text Processing
